[
  {
    "image": "logos/premcore.png",
    "name": "Premcore",
    "link": "https://google.com"
  },
  {
    "image": "logos/bioceuticals.png",
    "name": "Bioceuticals",
    "link": "https://google.com"
  },
  {
    "image": "logos/nfh.png",
    "name": "NFH",
    "link": "https://google.com"
  },
  {
    "image": "logos/bioceuticals.png",
    "name": "Bioceuticals",
    "link": "https://google.com"
  },
  {
    "image": "logos/premcore.png",
    "name": "Premcore",
    "link": "https://google.com"
  },
  {
    "image": "logos/nfh.png",
    "name": "NFH",
    "link": "https://google.com"
  }
]
